MANIFEST.in
README.md
requirements.txt
setup.py
rpctool/__init__.py
rpctool/__main__.py
rpctool/cover2rpc.py
rpctool/rpc_config.py
rpctool/utils.py
rpctool.egg-info/PKG-INFO
rpctool.egg-info/SOURCES.txt
rpctool.egg-info/dependency_links.txt
rpctool.egg-info/requires.txt
rpctool.egg-info/top_level.txt
rpctool/evaluate_v1/__init__.py
rpctool/evaluate_v1/analysisAndVis.py
rpctool/evaluate_v1/evaluate.py
rpctool/evaluate_v1/evaluateByBbox.py
rpctool/evaluate_v1/evaluateMap.py
rpctool/evaluate_v1/printAnd2latex.py